MoguiYuehuixueVer1/README.md
MoguiYuehuixueVer1/__init__.py
MoguiYuehuixueVer1/__main__.py
MoguiYuehuixueVer1/file.epub
MoguiYuehuixueVer1/index.html
MoguiYuehuixueVer1/css/__init__.py
MoguiYuehuixueVer1/css/annotations.css
MoguiYuehuixueVer1/css/main.css
MoguiYuehuixueVer1/css/normalize.css
MoguiYuehuixueVer1/css/popup.css
MoguiYuehuixueVer1/font/__init__.py
MoguiYuehuixueVer1/font/fontello.eot
MoguiYuehuixueVer1/font/fontello.svg
MoguiYuehuixueVer1/font/fontello.ttf
MoguiYuehuixueVer1/font/fontello.woff
MoguiYuehuixueVer1/img/__init__.py
MoguiYuehuixueVer1/img/annotator-glyph-sprite.png
MoguiYuehuixueVer1/img/annotator-icon-sprite.png
MoguiYuehuixueVer1/img/apple-touch-icon.png
MoguiYuehuixueVer1/img/cancelfullscreen.png
MoguiYuehuixueVer1/img/close.png
MoguiYuehuixueVer1/img/fullscreen.png
MoguiYuehuixueVer1/img/loader.gif
MoguiYuehuixueVer1/img/menu-icon.png
MoguiYuehuixueVer1/img/save.png
MoguiYuehuixueVer1/img/saved.png
MoguiYuehuixueVer1/img/settings-s.png
MoguiYuehuixueVer1/img/settings.png
MoguiYuehuixueVer1/img/star.png
MoguiYuehuixueVer1/js/__init__.py
MoguiYuehuixueVer1/js/epub.js
MoguiYuehuixueVer1/js/epub.min.js
MoguiYuehuixueVer1/js/epub.min.map
MoguiYuehuixueVer1/js/hooks.min.js
MoguiYuehuixueVer1/js/hooks.min.map
MoguiYuehuixueVer1/js/reader.js
MoguiYuehuixueVer1/js/reader.js.map
MoguiYuehuixueVer1/js/reader.min.js
MoguiYuehuixueVer1/js/reader.min.map
MoguiYuehuixueVer1/js/hooks/__init__.py
MoguiYuehuixueVer1/js/hooks/extensions/__init__.py
MoguiYuehuixueVer1/js/hooks/extensions/highlight.js
MoguiYuehuixueVer1/js/libs/__init__.py
MoguiYuehuixueVer1/js/libs/jquery.min.js
MoguiYuehuixueVer1/js/libs/localforage.min.js
MoguiYuehuixueVer1/js/libs/screenfull.js
MoguiYuehuixueVer1/js/libs/screenfull.min.js
MoguiYuehuixueVer1/js/libs/zip.min.js
MoguiYuehuixueVer1/js/plugins/__init__.py
MoguiYuehuixueVer1/js/plugins/hypothesis.js
MoguiYuehuixueVer1/js/plugins/search.js
mogui_yuehuixue_ver1-2022.10.11.0.dist-info/METADATA
mogui_yuehuixue_ver1-2022.10.11.0.dist-info/WHEEL
mogui_yuehuixue_ver1-2022.10.11.0.dist-info/entry_points.txt
mogui_yuehuixue_ver1-2022.10.11.0.dist-info/top_level.txt
mogui_yuehuixue_ver1-2022.10.11.0.dist-info/RECORD
